Workbook

Sheet Start_Here
B2: Interest Rate Risk Problem Set — Fully Worked Excel File
B4: Workbook contents
B5: Part1 | C5: Bond pricing and sensitivity to a +1% yield shock; includes ranking by interest-rate sensitivity.
B6: Part2 | C6: Step-by-step duration build for a 4-year, 6% coupon bond at a 7% yield; includes actual vs estimated price changes.
B7: Part3 | C7: Three duration comparison panels showing the effects of maturity, coupon, and yield.
B8: Part4 | C8: Yield-curve pricing with spot rates and a steepening example; compares full-curve pricing with a flat-yield shortcut.
B9: Part5 | C9: Convexity demonstration using a 25-year, 4% coupon bond; compares actual changes, duration-only estimates, and duration+convexity estimates.
B10: Solution_Summary | C10: Instructor-facing summary of the main answers linked directly from the calculations.
B12: Color/format legend
B13: Blue font | C13: Hardcoded instructor inputs students can change in class
B14: Black font | C14: Formulas and derived outputs
B15: Gray fill | C15: Labels or static headings
B16: Yellow fill | C16: Key assumptions or cells worth reviewing
B17: Currency / % formats | C17: Prices, durations, and changes are preformatted for readability
B20: Notes | C20: All calculations use annual coupon payments and a $1,000 par value unless otherwise noted.
C22: This workbook is fully worked: formulas are embedded throughout, and the Solution_Summary sheet links the main answers.

Sheet Part1
A1: Part 1 — Price–Yield Intuition and Bond Ranking
A3: Task | B3: Compute each bond's price, reprice after a +1.0% yield shock, and rank the bonds by interest-rate sensitivity. | N3: Yield shock | O3: Applied to each bond's current yield
N4: 0.01
A5: Bond | B5: Coupon Rate | C5: Maturity (yrs) | D5: Yield | E5: Par | F5: Coupon ($) | G5: Price @ current yield | H5: Yield + shock | I5: Price @ shocked yield | J5: % price change | K5: Abs. % change | L5: Sensitivity rank
A6: A | B6: 0.09 | C6: 4 | D6: 0.07 | E6: 1000 | F6: =B6*E6 -> 90 | G6: =-PV(D6,C6,F6,E6) -> 1067.7442 | H6: =D6+$N$4 -> 0.08 | I6: =-PV(H6,C6,F6,E6) -> 1033.1213 | J6: =I6/G6-1 -> -0.032426265 | K6: =ABS(J6) -> 0.032426265 | L6: =RANK(K6,$K$6:$K$9,0) -> 4 | N6: Most sensitive bond | O6: =INDEX($A$6:$A$9,MATCH(MAX($K$6:$K$9),$K$6:$K$9,0)) -> D
A7: B | B7: 0.09 | C7: 25 | D7: 0.07 | E7: 1000 | F7: =B7*E7 -> 90 | G7: =-PV(D7,C7,F7,E7) -> 1233.0717 | H7: =D7+$N$4 -> 0.08 | I7: =-PV(H7,C7,F7,E7) -> 1106.7478 | J7: =I7/G7-1 -> -0.10244652 | K7: =ABS(J7) -> 0.10244652 | L7: =RANK(K7,$K$6:$K$9,0) -> 3 | N7: Least sensitive bond | O7: =INDEX($A$6:$A$9,MATCH(MIN($K$6:$K$9),$K$6:$K$9,0)) -> A
A8: C | B8: 0.04 | C8: 25 | D8: 0.07 | E8: 1000 | F8: =B8*E8 -> 40 | G8: =-PV(D8,C8,F8,E8) -> 650.3925 | H8: =D8+$N$4 -> 0.08 | I8: =-PV(H8,C8,F8,E8) -> 573.00895 | J8: =I8/G8-1 -> -0.11897977 | K8: =ABS(J8) -> 0.11897977 | L8: =RANK(K8,$K$6:$K$9,0) -> 2 | N8: Teaching note | O8: Longest maturity + lowest coupon + lowest starting yield gives the largest price response.
A9: D | B9: 0.04 | C9: 25 | D9: 0.05 | E9: 1000 | F9: =B9*E9 -> 40 | G9: =-PV(D9,C9,F9,E9) -> 859.06055 | H9: =D9+$N$4 -> 0.06 | I9: =-PV(H9,C9,F9,E9) -> 744.33288 | J9: =I9/G9-1 -> -0.13355016 | K9: =ABS(J9) -> 0.13355016 | L9: =RANK(K9,$K$6:$K$9,0) -> 1

Sheet Sheet1
B1: Bond A | C1: Bond B | D1: Bond C | E1: Bond D
A2: Maturity | B2: 4 | C2: 25 | D2: 25 | E2: 25
A3: Coupon Rate | B3: 0.09 | C3: 0.09 | D3: 0.04 | E3: 0.04
A4: Yield | B4: 0.07 | C4: 0.07 | D4: 0.07 | E4: 0.05
A5: Par Value | B5: 1000 | C5: 1000 | D5: 1000 | E5: 1000
A6: Price | B6: =-PV(B4/2,B2*2,B3/2*B5,B5) -> 1068.7396 | C6: =-PV(C4/2,C2*2,C3/2*C5,C5) -> 1234.5562 | D6: =-PV(D4/2,D2*2,D3/2*D5,D5) -> 648.16573 | E6: =-PV(E4/2,E2*2,E3/2*E5,E5) -> 858.18844
A7: Price with +1% yield | B7: =-PV((B4+0.01)/2,B2*2,B3/2*B5,B5) -> 1033.6637 | C7: =-PV((C4+0.01)/2,C2*2,C3/2*C5,C5) -> 1107.4109 | D7: =-PV((D4+0.01)/2,D2*2,D3/2*D5,D5) -> 570.35631 | E7: =-PV((E4+0.01)/2,E2*2,E3/2*E5,E5) -> 742.70236
A8: Duration | B8: =SUM(E15:E74)/2/(1+B4/2) -> 3.3501349 | C8: =SUM(I15:I74)/2/(1+C4/2) -> 11.212862 | D8: =SUM(M15:M74)/2/(1+D4/2) -> 13.199031 | E8: =SUM(Q15:Q74)/2/(1+E4/2) -> 14.873371
A9: True Change | B9: =B7/B6-1 -> -0.032819812 | C9: =C7/C6-1 -> -0.10298863 | D9: =D7/D6-1 -> -0.12004557 | E9: =E7/E6-1 -> -0.13456961
A10: Approx Change | B10: =-B8*0.01 -> -0.033501349 | C10: =-C8*0.01 -> -0.11212862 | D10: =-D8*0.01 -> -0.13199031 | E10: =-E8*0.01 -> -0.14873371
A11: Approx Change (with convexity) | D11: =D10+1/2*254*0.01^2 -> -0.11929031 | E11: =E10+1/2*305*0.01^2 -> -0.13348371
B13: Bond A | F13: Bond B | J13: Bond C | N13: Bond D
A14: Period | B14: Cash Flow | C14: Discounted Cash Flow | D14: Weight | E14: Weighted Maturity | F14: Cash Flow | G14: Discounted Cash Flow | H14: Weight | I14: Weighted Maturity | J14: Cash Flow | K14: Discounted Cash Flow | L14: Weight | M14: Weighted Maturity | N14: Cash Flow | O14: Discounted Cash Flow | P14: Weight | Q14: Weighted Maturity
A15: 1 | B15: =IF(A15=2*$B$2, $B$5 + $B$3/2*$B$5, IF(A15>2*$B$2,0, $B$3/2*$B$5)) -> 45 | C15: =B15/(1+$B$4/2)^A15 -> 43.478261 | D15: =C15/SUM($C$15:$C$74) -> 0.040681811 | E15: =D15*A15 -> 0.040681811 | F15: =IF(A15=2*$C$2, $C$5 + $C$3/2*$C$5, IF(A15>2*$C$2,0, $C$3/2*$C$5)) -> 45 | G15: =F15/(1+$C$4/2)^$A15 -> 43.478261 | H15: =G15/SUM($G$15:$G$74) -> 0.035217726 | I15: =H15*A15 -> 0.035217726 | J15: =IF(A15=2*$D$2, $D$5 + $D$3/2*$D$5, IF(A15>2*$D$2,0, $D$3/2*$D$5)) -> 20 | K15: =J15/(1+$D$4/2)^A15 -> 19.323671 | L15: =K15/SUM($K$15:$K$74) -> 0.029812856 | M15: =L15*A15 -> 0.029812856 | N15: =IF(A15=2*$E$2, $E$5 + $E$3/2*$E$5, IF(A15>2*$E$2,0, $E$3/2*$E$5)) -> 20 | O15: =N15/(1+$E$4/2)^A15 -> 19.512195 | P15: =O15/SUM($O$15:$O$74) -> 0.022736493 | Q15: =P15*A15 -> 0.022736493
A16: 2 | B16: =IF(A16=2*$B$2, $B$5 + $B$3/2*$B$5, IF(A16>2*$B$2,0, $B$3/2*$B$5)) -> 45 | C16: =B16/(1+$B$4/2)^A16 -> 42.007982 | D16: =C16/SUM($C$15:$C$74) -> 0.039306098 | E16: =D16*A16 -> 0.078612196 | F16: =IF(A16=2*$C$2, $C$5 + $C$3/2*$C$5, IF(A16>2*$C$2,0, $C$3/2*$C$5)) -> 45 | G16: =F16/(1+$C$4/2)^$A16 -> 42.007982 | H16: =G16/SUM($G$15:$G$74) -> 0.034026788 | I16: =H16*A16 -> 0.068053576 | J16: =IF(A16=2*$D$2, $D$5 + $D$3/2*$D$5, IF(A16>2*$D$2,0, $D$3/2*$D$5)) -> 20 | K16: =J16/(1+$D$4/2)^A16 -> 18.670214 | L16: =K16/SUM($K$15:$K$74) -> 0.028804692 | M16: =L16*A16 -> 0.057609383 | N16: =IF(A16=2*$E$2, $E$5 + $E$3/2*$E$5, IF(A16>2*$E$2,0, $E$3/2*$E$5)) -> 20 | O16: =N16/(1+$E$4/2)^A16 -> 19.036288 | P16: =O16/SUM($O$15:$O$74) -> 0.022181944 | Q16: =P16*A16 -> 0.044363888
A17: 3 | B17: =IF(A17=2*$B$2, $B$5 + $B$3/2*$B$5, IF(A17>2*$B$2,0, $B$3/2*$B$5)) -> 45 | C17: =B17/(1+$B$4/2)^A17 -> 40.587422 | D17: =C17/SUM($C$15:$C$74) -> 0.037976906 | E17: =D17*A17 -> 0.11393072 | F17: =IF(A17=2*$C$2, $C$5 + $C$3/2*$C$5, IF(A17>2*$C$2,0, $C$3/2*$C$5)) -> 45 | G17: =F17/(1+$C$4/2)^$A17 -> 40.587422 | H17: =G17/SUM($G$15:$G$74) -> 0.032876124 | I17: =H17*A17 -> 0.098628371 | J17: =IF(A17=2*$D$2, $D$5 + $D$3/2*$D$5, IF(A17>2*$D$2,0, $D$3/2*$D$5)) -> 20 | K17: =J17/(1+$D$4/2)^A17 -> 18.038854 | L17: =K17/SUM($K$15:$K$74) -> 0.02783062 | M17: =L17*A17 -> 0.08349186 | N17: =IF(A17=2*$E$2, $E$5 + $E$3/2*$E$5, IF(A17>2*$E$2,0, $E$3/2*$E$5)) -> 20 | O17: =N17/(1+$E$4/2)^A17 -> 18.571988 | P17: =O17/SUM($O$15:$O$74) -> 0.021640921 | Q17: =P17*A17 -> 0.064922763
A18: 4 | B18: =IF(A18=2*$B$2, $B$5 + $B$3/2*$B$5, IF(A18>2*$B$2,0, $B$3/2*$B$5)) -> 45 | C18: =B18/(1+$B$4/2)^A18 -> 39.2149 | D18: =C18/SUM($C$15:$C$74) -> 0.036692663 | E18: =D18*A18 -> 0.14677065 | F18: =IF(A18=2*$C$2, $C$5 + $C$3/2*$C$5, IF(A18>2*$C$2,0, $C$3/2*$C$5)) -> 45 | G18: =F18/(1+$C$4/2)^$A18 -> 39.2149 | H18: =G18/SUM($G$15:$G$74) -> 0.031764371 | I18: =H18*A18 -> 0.12705748 | J18: =IF(A18=2*$D$2, $D$5 + $D$3/2*$D$5, IF(A18>2*$D$2,0, $D$3/2*$D$5)) -> 20 | K18: =J18/(1+$D$4/2)^A18 -> 17.428845 | L18: =K18/SUM($K$15:$K$74) -> 0.026889488 | M18: =L18*A18 -> 0.10755795 | N18: =IF(A18=2*$E$2, $E$5 + $E$3/2*$E$5, IF(A18>2*$E$2,0, $E$3/2*$E$5)) -> 20 | O18: =N18/(1+$E$4/2)^A18 -> 18.119013 | P18: =O18/SUM($O$15:$O$74) -> 0.021113094 | Q18: =P18*A18 -> 0.084452374
A19: 5 | B19: =IF(A19=2*$B$2, $B$5 + $B$3/2*$B$5, IF(A19>2*$B$2,0, $B$3/2*$B$5)) -> 45 | C19: =B19/(1+$B$4/2)^A19 -> 37.888793 | D19: =C19/SUM($C$15:$C$74) -> 0.035451848 | E19: =D19*A19 -> 0.17725924 | F19: =IF(A19=2*$C$2, $C$5 + $C$3/2*$C$5, IF(A19>2*$C$2,0, $C$3/2*$C$5)) -> 45 | G19: =F19/(1+$C$4/2)^$A19 -> 37.888793 | H19: =G19/SUM($G$15:$G$74) -> 0.030690213 | I19: =H19*A19 -> 0.15345107 | J19: =IF(A19=2*$D$2, $D$5 + $D$3/2*$D$5, IF(A19>2*$D$2,0, $D$3/2*$D$5)) -> 20 | K19: =J19/(1+$D$4/2)^A19 -> 16.839463 | L19: =K19/SUM($K$15:$K$74) -> 0.025980181 | M19: =L19*A19 -> 0.12990091 | N19: =IF(A19=2*$E$2, $E$5 + $E$3/2*$E$5, IF(A19>2*$E$2,0, $E$3/2*$E$5)) -> 20 | O19: =N19/(1+$E$4/2)^A19 -> 17.677086 | P19: =O19/SUM($O$15:$O$74) -> 0.02059814 | Q19: =P19*A19 -> 0.1029907
A20: 6 | B20: =IF(A20=2*$B$2, $B$5 + $B$3/2*$B$5, IF(A20>2*$B$2,0, $B$3/2*$B$5)) -> 45 | C20: =B20/(1+$B$4/2)^A20 -> 36.607529 | D20: =C20/SUM($C$15:$C$74) -> 0.034252993 | E20: =D20*A20 -> 0.20551796 | F20: =IF(A20=2*$C$2, $C$5 + $C$3/2*$C$5, IF(A20>2*$C$2,0, $C$3/2*$C$5)) -> 45 | G20: =F20/(1+$C$4/2)^$A20 -> 36.607529 | H20: =G20/SUM($G$15:$G$74) -> 0.02965238 | I20: =H20*A20 -> 0.17791428 | J20: =IF(A20=2*$D$2, $D$5 + $D$3/2*$D$5, IF(A20>2*$D$2,0, $D$3/2*$D$5)) -> 20 | K20: =J20/(1+$D$4/2)^A20 -> 16.270013 | L20: =K20/SUM($K$15:$K$74) -> 0.025101625 | M20: =L20*A20 -> 0.15060975 | N20: =IF(A20=2*$E$2, $E$5 + $E$3/2*$E$5, IF(A20>2*$E$2,0, $E$3/2*$E$5)) -> 20 | O20: =N20/(1+$E$4/2)^A20 -> 17.245937 | P20: =O20/SUM($O$15:$O$74) -> 0.020095746 | Q20: =P20*A20 -> 0.12057448
A21: 7 | B21: =IF(A21=2*$B$2, $B$5 + $B$3/2*$B$5, IF(A21>2*$B$2,0, $B$3/2*$B$5)) -> 45 | C21: =B21/(1+$B$4/2)^A21 -> 35.369593 | D21: =C21/SUM($C$15:$C$74) -> 0.03309468 | E21: =D21*A21 -> 0.23166276 | F21: =IF(A21=2*$C$2, $C$5 + $C$3/2*$C$5, IF(A21>2*$C$2,0, $C$3/2*$C$5)) -> 45 | G21: =F21/(1+$C$4/2)^$A21 -> 35.369593 | H21: =G21/SUM($G$15:$G$74) -> 0.028649643 | I21: =H21*A21 -> 0.2005475 | J21: =IF(A21=2*$D$2, $D$5 + $D$3/2*$D$5, IF(A21>2*$D$2,0, $D$3/2*$D$5)) -> 20 | K21: =J21/(1+$D$4/2)^A21 -> 15.719819 | L21: =K21/SUM($K$15:$K$74) -> 0.024252777 | M21: =L21*A21 -> 0.16976944 | N21: =IF(A21=2*$E$2, $E$5 + $E$3/2*$E$5, IF(A21>2*$E$2,0, $E$3/2*$E$5)) -> 20 | O21: =N21/(1+$E$4/2)^A21 -> 16.825305 | P21: =O21/SUM($O$15:$O$74) -> 0.019605606 | Q21: =P21*A21 -> 0.13723924
A22: 8 | B22: =IF(A22=2*$B$2, $B$5 + $B$3/2*$B$5, IF(A22>2*$B$2,0, $B$3/2*$B$5)) -> 1045 | C22: =B22/(1+$B$4/2)^A22 -> 793.58508 | D22: =C22/SUM($C$15:$C$74) -> 0.742543 | E22: =D22*A22 -> 5.940344 | F22: =IF(A22=2*$C$2, $C$5 + $C$3/2*$C$5, IF(A22>2*$C$2,0, $C$3/2*$C$5)) -> 45 | G22: =F22/(1+$C$4/2)^$A22 -> 34.17352 | H22: =G22/SUM($G$15:$G$74) -> 0.027680814 | I22: =H22*A22 -> 0.22144651 | J22: =IF(A22=2*$D$2, $D$5 + $D$3/2*$D$5, IF(A22>2*$D$2,0, $D$3/2*$D$5)) -> 20 | K22: =J22/(1+$D$4/2)^A22 -> 15.188231 | L22: =K22/SUM($K$15:$K$74) -> 0.023432635 | M22: =L22*A22 -> 0.18746108 | N22: =IF(A22=2*$E$2, $E$5 + $E$3/2*$E$5, IF(A22>2*$E$2,0, $E$3/2*$E$5)) -> 20 | O22: =N22/(1+$E$4/2)^A22 -> 16.414931 | P22: =O22/SUM($O$15:$O$74) -> 0.019127421 | Q22: =P22*A22 -> 0.15301937
A23: 9 | B23: =IF(A23=2*$B$2, $B$5 + $B$3/2*$B$5, IF(A23>2*$B$2,0, $B$3/2*$B$5)) -> 0 | C23: =B23/(1+$B$4/2)^A23 -> 0 | D23: =C23/SUM($C$15:$C$74) -> 0 | E23: =D23*A23 -> 0 | F23: =IF(A23=2*$C$2, $C$5 + $C$3/2*$C$5, IF(A23>2*$C$2,0, $C$3/2*$C$5)) -> 45 | G23: =F23/(1+$C$4/2)^$A23 -> 33.017894 | H23: =G23/SUM($G$15:$G$74) -> 0.026744748 | I23: =H23*A23 -> 0.24070273 | J23: =IF(A23=2*$D$2, $D$5 + $D$3/2*$D$5, IF(A23>2*$D$2,0, $D$3/2*$D$5)) -> 20 | K23: =J23/(1+$D$4/2)^A23 -> 14.674619 | L23: =K23/SUM($K$15:$K$74) -> 0.022640227 | M23: =L23*A23 -> 0.20376204 | N23: =IF(A23=2*$E$2, $E$5 + $E$3/2*$E$5, IF(A23>2*$E$2,0, $E$3/2*$E$5)) -> 20 | O23: =N23/(1+$E$4/2)^A23 -> 16.014567 | P23: =O23/SUM($O$15:$O$74) -> 0.018660898 | Q23: =P23*A23 -> 0.16794808
A24: 10 | B24: =IF(A24=2*$B$2, $B$5 + $B$3/2*$B$5, IF(A24>2*$B$2,0, $B$3/2*$B$5)) -> 0 | C24: =B24/(1+$B$4/2)^A24 -> 0 | D24: =C24/SUM($C$15:$C$74) -> 0 | E24: =D24*A24 -> 0 | F24: =IF(A24=2*$C$2, $C$5 + $C$3/2*$C$5, IF(A24>2*$C$2,0, $C$3/2*$C$5)) -> 45 | G24: =F24/(1+$C$4/2)^$A24 -> 31.901347 | H24: =G24/SUM($G$15:$G$74) -> 0.025840336 | I24: =H24*A24 -> 0.25840336 | J24: =IF(A24=2*$D$2, $D$5 + $D$3/2*$D$5, IF(A24>2*$D$2,0, $D$3/2*$D$5)) -> 20 | K24: =J24/(1+$D$4/2)^A24 -> 14.178376 | L24: =K24/SUM($K$15:$K$74) -> 0.021874616 | M24: =L24*A24 -> 0.21874616 | N24: =IF(A24=2*$E$2, $E$5 + $E$3/2*$E$5, IF(A24>2*$E$2,0, $E$3/2*$E$5)) -> 20 | O24: =N24/(1+$E$4/2)^A24 -> 15.623968 | P24: =O24/SUM($O$15:$O$74) -> 0.018205754 | Q24: =P24*A24 -> 0.18205754
A25: 11 | B25: =IF(A25=2*$B$2, $B$5 + $B$3/2*$B$5, IF(A25>2*$B$2,0, $B$3/2*$B$5)) -> 0 | C25: =B25/(1+$B$4/2)^A25 -> 0 | D25: =C25/SUM($C$15:$C$74) -> 0 | E25: =D25*A25 -> 0 | F25: =IF(A25=2*$C$2, $C$5 + $C$3/2*$C$5, IF(A25>2*$C$2,0, $C$3/2*$C$5)) -> 45 | G25: =F25/(1+$C$4/2)^$A25 -> 30.822557 | H25: =G25/SUM($G$15:$G$74) -> 0.024966508 | I25: =H25*A25 -> 0.27463159 | J25: =IF(A25=2*$D$2, $D$5 + $D$3/2*$D$5, IF(A25>2*$D$2,0, $D$3/2*$D$5)) -> 20 | K25: =J25/(1+$D$4/2)^A25 -> 13.698914 | L25: =K25/SUM($K$15:$K$74) -> 0.021134894 | M25: =L25*A25 -> 0.23248384 | N25: =IF(A25=2*$E$2, $E$5 + $E$3/2*$E$5, IF(A25>2*$E$2,0, $E$3/2*$E$5)) -> 20 | O25: =N25/(1+$E$4/2)^A25 -> 15.242896 | P25: =O25/SUM($O$15:$O$74) -> 0.017761712 | Q25: =P25*A25 -> 0.19537883
A26: 12 | B26: =IF(A26=2*$B$2, $B$5 + $B$3/2*$B$5, IF(A26>2*$B$2,0, $B$3/2*$B$5)) -> 0 | C26: =B26/(1+$B$4/2)^A26 -> 0 | D26: =C26/SUM($C$15:$C$74) -> 0 | E26: =D26*A26 -> 0 | F26: =IF(A26=2*$C$2, $C$5 + $C$3/2*$C$5, IF(A26>2*$C$2,0, $C$3/2*$C$5)) -> 45 | G26: =F26/(1+$C$4/2)^$A26 -> 29.780248 | H26: =G26/SUM($G$15:$G$74) -> 0.02412223 | I26: =H26*A26 -> 0.28946676 | J26: =IF(A26=2*$D$2, $D$5 + $D$3/2*$D$5, IF(A26>2*$D$2,0, $D$3/2*$D$5)) -> 20 | K26: =J26/(1+$D$4/2)^A26 -> 13.235666 | L26: =K26/SUM($K$15:$K$74) -> 0.020420188 | M26: =L26*A26 -> 0.24504225 | N26: =IF(A26=2*$E$2, $E$5 + $E$3/2*$E$5, IF(A26>2*$E$2,0, $E$3/2*$E$5)) -> 20 | O26: =N26/(1+$E$4/2)^A26 -> 14.871118 | P26: =O26/SUM($O$15:$O$74) -> 0.017328499 | Q26: =P26*A26 -> 0.20794199
... A74: 60 | B74: =IF(A74=2*$B$2, $B$5 + $B$3/2*$B$5, IF(A74>2*$B$2,0, $B$3/2*$B$5)) -> 0 | C74: =B74/(1+$B$4/2)^A74 -> 0 | D74: =C74/SUM($C$15:$C$74) -> 0 | E74: =D74*A74 -> 0 | F74: =IF(A74=2*$C$2, $C$5 + $C$3/2*$C$5, IF(A74>2*$C$2,0, $C$3/2*$C$5)) -> 0 | G74: =F74/(1+$C$4/2)^$A74 -> 0 | H74: =G74/SUM($G$15:$G$74) -> 0 | I74: =H74*A74 -> 0 | J74: =IF(A74=2*$D$2, $D$5 + $D$3/2*$D$5, IF(A74>2*$D$2,0, $D$3/2*$D$5)) -> 0 | K74: =J74/(1+$D$4/2)^A74 -> 0 | L74: =K74/SUM($K$15:$K$74) -> 0 | M74: =L74*A74 -> 0 | N74: =IF(A74=2*$E$2, $E$5 + $E$3/2*$E$5, IF(A74>2*$E$2,0, $E$3/2*$E$5)) -> 0 | O74: =N74/(1+$E$4/2)^A74 -> 0 | P74: =O74/SUM($O$15:$O$74) -> 0 | Q74: =P74*A74 -> 0

Sheet Part2
A1: Part 2 — Step-by-Step Duration Calculation
A3: Inputs | H3: Summary answers
B4: Par value | C4: 1000 | H4: Macaulay duration | I4: =SUM(F13:F16) -> 3.6666955
B5: Coupon rate | C5: 0.06 | H5: Modified duration | I5: =I4/(1+$C$6) -> 3.4268182
B6: Yield | C6: 0.07 | H6: Shock size (Δy) | I6: 0.01
B7: Maturity (yrs) | C7: 4 | H7: Price if yield rises by Δy | I7: =-PV($C$6+$I$6,$C$7,$C$8,$C$4) -> 933.75746
B8: Coupon ($) | C8: =C4*C5 -> 60 | H8: Actual % change (yield up) | I8: =I7/$C$9-1 -> -0.03350532
B9: Price | C9: =-PV(C6,C7,C8,C4) -> 966.12789 | H9: Duration estimate (yield up) | I9: =-I5*I6 -> -0.034268182
H10: Estimate error (up) | I10: =I9-I8 -> -0.00076286158
H11: Price if yield falls by Δy | I11: =-PV($C$6-$I$6,$C$7,$C$8,$C$4) -> 1000
A12: Period | B12: Cash flow | C12: Discount factor | D12: PV | E12: Weight | F12: t × Weight | H12: Actual % change (yield down) | I12: =I11/$C$9-1 -> 0.035059657
A13: 1 | B13: =IF(A13<$C$7,$C$8,$C$8+$C$4) -> 60 | C13: =(1+$C$6)^A13 -> 1.07 | D13: =B13/C13 -> 56.074766 | E13: =D13/$C$9 -> 0.058040728 | F13: =A13*E13 -> 0.058040728 | H13: Duration estimate (yield down) | I13: =I5*I6 -> 0.034268182
A14: 2 | B14: =IF(A14<$C$7,$C$8,$C$8+$C$4) -> 60 | C14: =(1+$C$6)^A14 -> 1.1449 | D14: =B14/C14 -> 52.406324 | E14: =D14/$C$9 -> 0.054243671 | F14: =A14*E14 -> 0.10848734 | H14: Estimate error (down) | I14: =I13-I12 -> -0.00079147543
A15: 3 | B15: =IF(A15<$C$7,$C$8,$C$8+$C$4) -> 60 | C15: =(1+$C$6)^A15 -> 1.225043 | D15: =B15/C15 -> 48.977873 | E15: =D15/$C$9 -> 0.05069502 | F15: =A15*E15 -> 0.15208506
A16: 4 | B16: =IF(A16<$C$7,$C$8,$C$8+$C$4) -> 1060 | C16: =(1+$C$6)^A16 -> 1.310796 | D16: =B16/C16 -> 808.66892 | E16: =D16/$C$9 -> 0.83702058 | F16: =A16*E16 -> 3.3480823
A19: Interpretation | B19: Modified duration is the approximate % price change for a 1.00 change in yield. For a +1.0% move, multiply modified duration by 0.01. The estimate is close but not exact because the price–yield relationship is curved.

Sheet Part3
A1: Part 3 — How Bond Characteristics Affect Duration
A3: Summary output columns | H3: Helper PV-by-period columns
A4: Scenario | B4: Coupon rate | C4: Yield | D4: Maturity | E4: Price | F4: Macaulay duration | G4: Modified duration | H4: 1 | I4: 2 | J4: 3 | K4: 4 | L4: 5 | M4: 6 | N4: 7 | O4: 8 | P4: 9 | Q4: 10 | R4: 11 | S4: 12 | T4: 13 | U4: 14 | V4: 15 | W4: 16 | X4: 17 | Y4: 18 | Z4: 19 | AA4: 20
A6: A. Maturity effect (coupon = 8%, yield = 6%)
A7: 5-year, 8% coupon, 6% yield | B7: 0.08 | C7: 0.06 | D7: 5 | E7: =SUM(H7:AA7) -> 1084.2473 | F7: =SUMPRODUCT(H7:AA7,$H$4:$AA$4)/E7 -> 4.3422234 | G7: =F7/(1+C7) -> 4.0964371 | H7: =IF(H$4<=$D7,IF(H$4=$D7,$B7*1000+1000,$B7*1000)/(1+$C7)^H$4,0) -> 75.471698 | I7: =IF(I$4<=$D7,IF(I$4=$D7,$B7*1000+1000,$B7*1000)/(1+$C7)^I$4,0) -> 71.199715 | J7: =IF(J$4<=$D7,IF(J$4=$D7,$B7*1000+1000,$B7*1000)/(1+$C7)^J$4,0) -> 67.169543 | K7: =IF(K$4<=$D7,IF(K$4=$D7,$B7*1000+1000,$B7*1000)/(1+$C7)^K$4,0) -> 63.367493 | L7: =IF(L$4<=$D7,IF(L$4=$D7,$B7*1000+1000,$B7*1000)/(1+$C7)^L$4,0) -> 807.03883 | M7: =IF(M$4<=$D7,IF(M$4=$D7,$B7*1000+1000,$B7*1000)/(1+$C7)^M$4,0) -> 0 | N7: =IF(N$4<=$D7,IF(N$4=$D7,$B7*1000+1000,$B7*1000)/(1+$C7)^N$4,0) -> 0 | O7: =IF(O$4<=$D7,IF(O$4=$D7,$B7*1000+1000,$B7*1000)/(1+$C7)^O$4,0) -> 0 | ... AA7: =IF(AA$4<=$D7,IF(AA$4=$D7,$B7*1000+1000,$B7*1000)/(1+$C7)^AA$4,0) -> 0
A8: 20-year, 8% coupon, 6% yield | B8: 0.08 | C8: 0.06 | D8: 20 | E8: =SUM(H8:AA8) -> 1229.3984 | F8: =SUMPRODUCT(H8:AA8,$H$4:$AA$4)/E8 -> 11.495154 | G8: =F8/(1+C8) -> 10.844485 | H8: =IF(H$4<=$D8,IF(H$4=$D8,$B8*1000+1000,$B8*1000)/(1+$C8)^H$4,0) -> 75.471698 | I8: =IF(I$4<=$D8,IF(I$4=$D8,$B8*1000+1000,$B8*1000)/(1+$C8)^I$4,0) -> 71.199715 | J8: =IF(J$4<=$D8,IF(J$4=$D8,$B8*1000+1000,$B8*1000)/(1+$C8)^J$4,0) -> 67.169543 | K8: =IF(K$4<=$D8,IF(K$4=$D8,$B8*1000+1000,$B8*1000)/(1+$C8)^K$4,0) -> 63.367493 | L8: =IF(L$4<=$D8,IF(L$4=$D8,$B8*1000+1000,$B8*1000)/(1+$C8)^L$4,0) -> 59.780654 | M8: =IF(M$4<=$D8,IF(M$4=$D8,$B8*1000+1000,$B8*1000)/(1+$C8)^M$4,0) -> 56.396843 | N8: =IF(N$4<=$D8,IF(N$4=$D8,$B8*1000+1000,$B8*1000)/(1+$C8)^N$4,0) -> 53.204569 | O8: =IF(O$4<=$D8,IF(O$4=$D8,$B8*1000+1000,$B8*1000)/(1+$C8)^O$4,0) -> 50.19299 | ... AA8: =IF(AA$4<=$D8,IF(AA$4=$D8,$B8*1000+1000,$B8*1000)/(1+$C8)^AA$4,0) -> 336.74911
A10: B. Coupon effect (maturity = 20 years, yield = 6%)
A11: 20-year, 8% coupon, 6% yield | B11: 0.08 | C11: 0.06 | D11: 20 | E11: =SUM(H11:AA11) -> 1229.3984 | F11: =SUMPRODUCT(H11:AA11,$H$4:$AA$4)/E11 -> 11.495154 | G11: =F11/(1+C11) -> 10.844485 | H11: =IF(H$4<=$D11,IF(H$4=$D11,$B11*1000+1000,$B11*1000)/(1+$C11)^H$4,0) -> 75.471698 | I11: =IF(I$4<=$D11,IF(I$4=$D11,$B11*1000+1000,$B11*1000)/(1+$C11)^I$4,0) -> 71.199715 | J11: =IF(J$4<=$D11,IF(J$4=$D11,$B11*1000+1000,$B11*1000)/(1+$C11)^J$4,0) -> 67.169543 | K11: =IF(K$4<=$D11,IF(K$4=$D11,$B11*1000+1000,$B11*1000)/(1+$C11)^K$4,0) -> 63.367493 | L11: =IF(L$4<=$D11,IF(L$4=$D11,$B11*1000+1000,$B11*1000)/(1+$C11)^L$4,0) -> 59.780654 | M11: =IF(M$4<=$D11,IF(M$4=$D11,$B11*1000+1000,$B11*1000)/(1+$C11)^M$4,0) -> 56.396843 | N11: =IF(N$4<=$D11,IF(N$4=$D11,$B11*1000+1000,$B11*1000)/(1+$C11)^N$4,0) -> 53.204569 | O11: =IF(O$4<=$D11,IF(O$4=$D11,$B11*1000+1000,$B11*1000)/(1+$C11)^O$4,0) -> 50.19299 | ... AA11: =IF(AA$4<=$D11,IF(AA$4=$D11,$B11*1000+1000,$B11*1000)/(1+$C11)^AA$4,0) -> 336.74911
A12: 20-year, 2% coupon, 6% yield | B12: 0.02 | C12: 0.06 | D12: 20 | E12: =SUM(H12:AA12) -> 541.20315 | F12: =SUMPRODUCT(H12:AA12,$H$4:$AA$4)/E12 -> 15.170092 | G12: =F12/(1+C12) -> 14.311408 | H12: =IF(H$4<=$D12,IF(H$4=$D12,$B12*1000+1000,$B12*1000)/(1+$C12)^H$4,0) -> 18.867925 | I12: =IF(I$4<=$D12,IF(I$4=$D12,$B12*1000+1000,$B12*1000)/(1+$C12)^I$4,0) -> 17.799929 | J12: =IF(J$4<=$D12,IF(J$4=$D12,$B12*1000+1000,$B12*1000)/(1+$C12)^J$4,0) -> 16.792386 | K12: =IF(K$4<=$D12,IF(K$4=$D12,$B12*1000+1000,$B12*1000)/(1+$C12)^K$4,0) -> 15.841873 | L12: =IF(L$4<=$D12,IF(L$4=$D12,$B12*1000+1000,$B12*1000)/(1+$C12)^L$4,0) -> 14.945163 | M12: =IF(M$4<=$D12,IF(M$4=$D12,$B12*1000+1000,$B12*1000)/(1+$C12)^M$4,0) -> 14.099211 | N12: =IF(N$4<=$D12,IF(N$4=$D12,$B12*1000+1000,$B12*1000)/(1+$C12)^N$4,0) -> 13.301142 | O12: =IF(O$4<=$D12,IF(O$4=$D12,$B12*1000+1000,$B12*1000)/(1+$C12)^O$4,0) -> 12.548247 | ... AA12: =IF(AA$4<=$D12,IF(AA$4=$D12,$B12*1000+1000,$B12*1000)/(1+$C12)^AA$4,0) -> 318.04082
A14: C. Yield effect (20-year zero coupon bond)
A15: 20-year zero, 8% yield | B15: 0 | C15: 0.08 | D15: 20 | E15: =SUM(H15:AA15) -> 214.54821 | F15: =SUMPRODUCT(H15:AA15,$H$4:$AA$4)/E15 -> 20 | G15: =F15/(1+C15) -> 18.518519 | H15: =IF(H$4<=$D15,IF(H$4=$D15,$B15*1000+1000,$B15*1000)/(1+$C15)^H$4,0) -> 0 | I15: =IF(I$4<=$D15,IF(I$4=$D15,$B15*1000+1000,$B15*1000)/(1+$C15)^I$4,0) -> 0 | J15: =IF(J$4<=$D15,IF(J$4=$D15,$B15*1000+1000,$B15*1000)/(1+$C15)^J$4,0) -> 0 | K15: =IF(K$4<=$D15,IF(K$4=$D15,$B15*1000+1000,$B15*1000)/(1+$C15)^K$4,0) -> 0 | L15: =IF(L$4<=$D15,IF(L$4=$D15,$B15*1000+1000,$B15*1000)/(1+$C15)^L$4,0) -> 0 | M15: =IF(M$4<=$D15,IF(M$4=$D15,$B15*1000+1000,$B15*1000)/(1+$C15)^M$4,0) -> 0 | N15: =IF(N$4<=$D15,IF(N$4=$D15,$B15*1000+1000,$B15*1000)/(1+$C15)^N$4,0) -> 0 | O15: =IF(O$4<=$D15,IF(O$4=$D15,$B15*1000+1000,$B15*1000)/(1+$C15)^O$4,0) -> 0 | ... AA15: =IF(AA$4<=$D15,IF(AA$4=$D15,$B15*1000+1000,$B15*1000)/(1+$C15)^AA$4,0) -> 214.54821
A16: 20-year zero, 3% yield | B16: 0 | C16: 0.03 | D16: 20 | E16: =SUM(H16:AA16) -> 553.67575 | F16: =SUMPRODUCT(H16:AA16,$H$4:$AA$4)/E16 -> 20 | G16: =F16/(1+C16) -> 19.417476 | H16: =IF(H$4<=$D16,IF(H$4=$D16,$B16*1000+1000,$B16*1000)/(1+$C16)^H$4,0) -> 0 | I16: =IF(I$4<=$D16,IF(I$4=$D16,$B16*1000+1000,$B16*1000)/(1+$C16)^I$4,0) -> 0 | J16: =IF(J$4<=$D16,IF(J$4=$D16,$B16*1000+1000,$B16*1000)/(1+$C16)^J$4,0) -> 0 | K16: =IF(K$4<=$D16,IF(K$4=$D16,$B16*1000+1000,$B16*1000)/(1+$C16)^K$4,0) -> 0 | L16: =IF(L$4<=$D16,IF(L$4=$D16,$B16*1000+1000,$B16*1000)/(1+$C16)^L$4,0) -> 0 | M16: =IF(M$4<=$D16,IF(M$4=$D16,$B16*1000+1000,$B16*1000)/(1+$C16)^M$4,0) -> 0 | N16: =IF(N$4<=$D16,IF(N$4=$D16,$B16*1000+1000,$B16*1000)/(1+$C16)^N$4,0) -> 0 | O16: =IF(O$4<=$D16,IF(O$4=$D16,$B16*1000+1000,$B16*1000)/(1+$C16)^O$4,0) -> 0 | ... AA16: =IF(AA$4<=$D16,IF(AA$4=$D16,$B16*1000+1000,$B16*1000)/(1+$C16)^AA$4,0) -> 553.67575
A19: Instructor notes
A20: • Maturity effect: | B20: Longer maturity increases duration because more cash flow weight sits far in the future.
A21: • Coupon effect: | B21: Lower coupons increase duration because less value is received early and more comes from distant principal.
A22: • Yield effect: | B22: For a zero-coupon bond, Macaulay duration equals maturity, but modified duration increases when yield falls.

Sheet Part5
B1: Part 5 - Convexity and Duration Approximation Error
B3: Inputs | E3: Summary answers | G3: Price-Yield Grid
B4: Par value | C4: 1000 | E4: Macaulay duration | F4: =SUM(G7:AE7) -> 15.455642 | G4: 1 | H4: 2 | I4: 3 | J4: 4 | K4: 5 | L4: 6 | M4: 7 | N4: 8 | O4: 9 | P4: 10 | Q4: 11 | R4: 12 | S4: 13 | T4: 14 | U4: 15 | V4: 16 | W4: 17 | X4: 18 | Y4: 19 | Z4: 20 | AA4: 21 | AB4: 22 | AC4: 23 | AD4: 24 | AE4: 25
B5: Coupon rate | C5: 0.04 | E5: Modified duration | F5: =F4/(1+$C$6) -> 14.719659 | H5: =IF(H$4<=$C$7,IF(H$4=$C$7,$C$9+$C$4,$C$9)/(1+$C$6)^H$4,0) -> 36.281179 | I5: =IF(I$4<=$C$7,IF(I$4=$C$7,$C$9+$C$4,$C$9)/(1+$C$6)^I$4,0) -> 34.553504 | J5: =IF(J$4<=$C$7,IF(J$4=$C$7,$C$9+$C$4,$C$9)/(1+$C$6)^J$4,0) -> 32.908099 | K5: =IF(K$4<=$C$7,IF(K$4=$C$7,$C$9+$C$4,$C$9)/(1+$C$6)^K$4,0) -> 31.341047 | L5: =IF(L$4<=$C$7,IF(L$4=$C$7,$C$9+$C$4,$C$9)/(1+$C$6)^L$4,0) -> 29.848616 | M5: =IF(M$4<=$C$7,IF(M$4=$C$7,$C$9+$C$4,$C$9)/(1+$C$6)^M$4,0) -> 28.427253 | N5: =IF(N$4<=$C$7,IF(N$4=$C$7,$C$9+$C$4,$C$9)/(1+$C$6)^N$4,0) -> 27.073574 | O5: =IF(O$4<=$C$7,IF(O$4=$C$7,$C$9+$C$4,$C$9)/(1+$C$6)^O$4,0) -> 25.784357 | ... AE5: =IF(AE$4<=$C$7,IF(AE$4=$C$7,$C$9+$C$4,$C$9)/(1+$C$6)^AE$4,0) -> 307.11488
B6: Yield | C6: 0.05 | E6: Approx. convexity | F6: =(C11+C12-2*C10)/(C10*C8^2) -> 305.12131 | G6: =IF($C$10=0,0,G5/$C$10) -> 0 | H6: =IF($C$10=0,0,H5/$C$10) -> 0.042233553 | I6: =IF($C$10=0,0,I5/$C$10) -> 0.040222431 | J6: =IF($C$10=0,0,J5/$C$10) -> 0.038307077 | K6: =IF($C$10=0,0,K5/$C$10) -> 0.036482931 | L6: =IF($C$10=0,0,L5/$C$10) -> 0.034745648 | M6: =IF($C$10=0,0,M5/$C$10) -> 0.033091094 | N6: =IF($C$10=0,0,N5/$C$10) -> 0.031515327 | ... AE6: =IF($C$10=0,0,AE5/$C$10) -> 0.35750085
B7: Maturity (yrs) | C7: 25 | E7: Actual % change (yield up) | F7: =C11/C10-1 -> -0.13355016 | G7: =G4*G6 -> 0 | H7: =H4*H6 -> 0.084467105 | I7: =I4*I6 -> 0.12066729 | J7: =J4*J6 -> 0.15322831 | K7: =K4*K6 -> 0.18241465 | L7: =L4*L6 -> 0.20847389 | M7: =M4*M6 -> 0.23163766 | N7: =N4*N6 -> 0.25212262 | ... AE7: =AE4*AE6 -> 8.9375214
B8: Shock size (Δy) | C8: 0.01 | E8: Duration-only est. (up) | F8: =-F5*$C$8 -> -0.14719659
B9: Coupon ($) | C9: =C4*C5 -> 40 | E9: Duration + convexity est. (up) | F9: =-F5*$C$8+0.5*F6*$C$8^2 -> -0.13194052 | G9: Yield | H9: Price | I9: % Chg vs Base
B10: Price at current yield | C10: =-PV(C6,C7,C9,C4) -> 859.06055 | E10: Error of duration-only (up) | F10: =F8-F7 -> -0.013646423 | G10: 0.02 | H10: =-PV(G10,$C$7,$C$9,$C$4) -> 1390.4691 | I10: =H10/$C$10-1 -> 0.61859269
B11: Price at y + Δy | C11: =-PV(C6+C8,C7,C9,C4) -> 744.33288 | E11: Error of dur.+convexity (up) | F11: =F9-F7 -> 0.0016096422 | G11: 0.03 | H11: =-PV(G11,$C$7,$C$9,$C$4) -> 1174.1315 | I11: =H11/$C$10-1 -> 0.36676218
B12: Price at y - Δy | C12: =-PV(C6-C8,C7,C9,C4) -> 1000 | E12: Actual % change (yield down) | F12: =C12/C10-1 -> 0.16406229 | G12: 0.04 | H12: =-PV(G12,$C$7,$C$9,$C$4) -> 1000 | I12: =H12/$C$10-1 -> 0.16406229
E13: Duration-only est. (down) | F13: =F5*$C$8 -> 0.14719659 | G13: 0.05 | H13: =-PV(G13,$C$7,$C$9,$C$4) -> 859.06055 | I13: =H13/$C$10-1 -> 0
E14: Duration + convexity est. (down) | F14: =F5*$C$8+0.5*F6*$C$8^2 -> 0.16245265 | G14: 0.06 | H14: =-PV(G14,$C$7,$C$9,$C$4) -> 744.33288 | I14: =H14/$C$10-1 -> -0.13355016
E15: Error of duration-only (down) | F15: =F13-F12 -> -0.016865708 | G15: 0.07 | H15: =-PV(G15,$C$7,$C$9,$C$4) -> 650.3925 | I15: =H15/$C$10-1 -> -0.24290261
E16: Error of dur.+convexity (down) | F16: =F14-F12 -> -0.0016096422 | G16: 0.08 | H16: =-PV(G16,$C$7,$C$9,$C$4) -> 573.00895 | I16: =H16/$C$10-1 -> -0.33298188
G17: 0.09 | H17: =-PV(G17,$C$7,$C$9,$C$4) -> 508.87102 | I17: =H17/$C$10-1 -> -0.40764243
B18: Teaching note: Compare the actual price changes in F7 and F12 with the duration-only estimates in F8 and F13. The convexity-adjusted estimates in F9 and F14 should be closer for a 1% yield shock. The price-yield grid on the right can be graphed manually in Excel if desired. | G18: 0.1 | H18: =-PV(G18,$C$7,$C$9,$C$4) -> 455.3776 | I18: =H18/$C$10-1 -> -0.46991211
G19: 0.11 | H19: =-PV(G19,$C$7,$C$9,$C$4) -> 410.47787 | I19: =H19/$C$10-1 -> -0.52217818
G20: 0.12 | H20: =-PV(G20,$C$7,$C$9,$C$4) -> 372.54887 | I20: =H20/$C$10-1 -> -0.56632991
B22: Helper rows: | C22: Row 5 = PV of each cash flow
C23: Row 6 = PV weight
C24: Row 7 = time x weight

Sheet Part4
A1: Part 4 — Yield Curve Pricing vs. Flat-Yield Shortcut
A3: Bond and term-structure inputs | J3: Summary answers
B4: Par value | C4: 1000 | J4: Baseline price (curve) | K4: =SUM(D15:D17) -> 1042.9606
B5: Annual coupon ($) | C5: 70 | J5: Baseline price (flat 5.5%) | K5: =SUM(E15:E17) -> 1040.469
B6: Maturity (yrs) | C6: 3 | J6: Steepened price (curve) | K6: =SUM(G15:G17) -> 1017.5325
B7: y1 | C7: 0.035 | J7: Steepened price (flat 6.5%) | K7: =SUM(H15:H17) -> 1013.2424
B8: y2 | C8: 0.045 | J8: $ change using curve | K8: =K6-K4 -> -25.428092
B9: y3 (baseline) | C9: 0.055 | J9: % change using curve | K9: =K6/K4-1 -> -0.024380684
B10: y3 (steepened) | C10: 0.065 | J10: $ change using flat shortcut | K10: =K7-K5 -> -27.226623
B11: Flat rate baseline | C11: =C9 -> 0.055 | J11: % change using flat shortcut | K11: =K7/K5-1 -> -0.026167645
B12: Flat rate steepened | C12: =C10 -> 0.065 | J12: Extra loss implied by flat shortcut | K12: =ABS(K11)-ABS(K9) -> 0.0017869603
A14: Period | B14: Cash flow | C14: Spot rate (baseline) | D14: PV (curve) | E14: PV (flat) | F14: Spot rate (steepened) | G14: PV (curve, new) | H14: PV (flat, new) | J14: Teaching note | K14: When only the 3-year rate rises, the flat-yield shortcut overstates the loss because it incorrectly reprices the year-1 and year-2 coupons at the higher rate.
A15: 1 | B15: =IF(A15<$C$6,$C$5,$C$5+$C$4) -> 70 | C15: =INDEX($C$7:$C$9,A15) -> 0.035 | D15: =B15/(1+C15)^A15 -> 67.63285 | E15: =B15/(1+$C$11)^A15 -> 66.350711 | F15: =IF(A15=3,$C$10,INDEX($C$7:$C$8,A15)) -> 0.035 | G15: =B15/(1+F15)^A15 -> 67.63285 | H15: =B15/(1+$C$12)^A15 -> 65.7277
A16: 2 | B16: =IF(A16<$C$6,$C$5,$C$5+$C$4) -> 70 | C16: =INDEX($C$7:$C$9,A16) -> 0.045 | D16: =B16/(1+C16)^A16 -> 64.101097 | E16: =B16/(1+$C$11)^A16 -> 62.891669 | F16: =IF(A16=3,$C$10,INDEX($C$7:$C$8,A16)) -> 0.045 | G16: =B16/(1+F16)^A16 -> 64.101097 | H16: =B16/(1+$C$12)^A16 -> 61.71615
A17: 3 | B17: =IF(A17<$C$6,$C$5,$C$5+$C$4) -> 1070 | C17: =INDEX($C$7:$C$9,A17) -> 0.055 | D17: =B17/(1+C17)^A17 -> 911.22662 | E17: =B17/(1+$C$11)^A17 -> 911.22662 | F17: =IF(A17=3,$C$10,INDEX($C$7:$C$8,A17)) -> 0.065 | G17: =B17/(1+F17)^A17 -> 885.79853 | H17: =B17/(1+$C$12)^A17 -> 885.79853

Sheet Solution_Summary
A1: Instructor Solution Summary
A4: Part 1: most sensitive bond | B4: =Part1!O6 -> D | C4: Bond D has the largest loss from a +1% yield shock.
A5: Part 1: least sensitive bond | B5: =Part1!O7 -> A | C5: Bond A has the smallest loss because its maturity is short.
A6: Part 2: price | B6: =Part2!C9 -> 966.12789 | C6: Current bond price for the 4-year, 6% coupon bond at 7% yield.
A7: Part 2: modified duration | B7: =Part2!I5 -> 3.4268182 | C7: Use this to approximate small % price changes.
A8: Part 2: actual % change if yield rises 1% | B8: =Part2!I8 -> -0.03350532 | C8: Compare this with the duration estimate in the next row.
A9: Part 2: duration estimate if yield rises 1% | B9: =Part2!I9 -> -0.034268182 | C9: The duration estimate is close, but not exact.
A10: Part 3: modified duration, 5-year 8% coupon | B10: =Part3!G7 -> 4.0964371 | C10: Shorter maturity lowers duration.
A11: Part 3: modified duration, 20-year 8% coupon | B11: =Part3!G8 -> 10.844485 | C11: Longer maturity raises duration.
A12: Part 3: modified duration, 20-year 2% coupon | B12: =Part3!G12 -> 14.311408 | C12: Lower coupon raises duration.
A13: Part 3: modified duration, 20-year zero at 8% | B13: =Part3!G15 -> 18.518519 | C13: Higher yield lowers modified duration.
A14: Part 3: modified duration, 20-year zero at 3% | B14: =Part3!G16 -> 19.417476 | C14: Lower yield raises modified duration.
A15: Part 4: baseline curve price | B15: =Part4!K4 -> 1042.9606 | C15: Uses maturity-specific spot rates for each cash flow.
A16: Part 4: steepened curve % change | B16: =Part4!K9 -> -0.024380684 | C16: Only the 3-year rate rises here.
A17: Part 4: flat-shortcut % change | B17: =Part4!K11 -> -0.026167645 | C17: The flat-yield shortcut overstates the loss.
A18: Part 5: modified duration | B18: =Part5!F5 -> 14.719659 | C18: Duration-only estimate is linear.
A19: Part 5: convexity | B19: =Part5!F6 -> 305.12131 | C19: Finite-difference convexity estimate.
A20: Part 5: actual % change if yield falls | B20: =Part5!F11 -> 0.0016096422 | C20: Actual gains are larger than duration-only predicts.
A21: Part 5: duration + convexity estimate if yield falls | B21: =Part5!F13 -> 0.14719659 | C21: Adding convexity improves the approximation.
A24: Recommended discussion prompts
A25: 1. | B25: Why does pushing value into distant cash flows raise duration?
A26: 2. | B26: Why does the flat-yield shortcut misstate the loss when only the long end of the curve steepens?
A27: 3. | B27: Why does convexity make large yield declines especially attractive for long-duration bonds?
